pycobol2csv/__init__.py
pycobol2csv/convert.py
pycobol2csv-1.0.6.dist-info/LICENSE
pycobol2csv-1.0.6.dist-info/METADATA
pycobol2csv-1.0.6.dist-info/WHEEL
pycobol2csv-1.0.6.dist-info/top_level.txt
pycobol2csv-1.0.6.dist-info/RECORD
