Metadata-Version: 2.1
Name: pycobol2csv
Version: 1.0.6
Summary: A Python library to convert COBOL ebcdic file to CSV format based on copybook
Home-page: https://github.com/jasonli-lijie/pycobol2csv
Download-URL: https://github.com/user/reponame/archive/v_01.tar.gz
Author: Jason Li
Author-email: niomobileapp@gmail.com
License: MIT
Project-URL: Bug Tracker, https://github.com/jasonli-lijie/pycobol2csv/issues
Keywords: COBOL,EBCDIC,CSV
Classifier: Development Status :: 5 - Production/Stable
Classifier: Intended Audience :: Developers
Classifier: Topic :: Software Development :: Build Tools
Classifier: License :: OSI Approved :: MIT License
Classifier: Programming Language :: Python :: 3
Classifier: Programming Language :: Python :: 3.6
Classifier: Programming Language :: Python :: 3.7
Classifier: Programming Language :: Python :: 3.8
Classifier: Programming Language :: Python :: 3.9
Classifier: Programming Language :: Python :: 3.10
Classifier: Programming Language :: Python :: 3.11
License-File: LICENSE
Requires-Dist: ebcdic
